PyCrowlingo/Classifier.py
PyCrowlingo/Client.py
PyCrowlingo/Concepts.py
PyCrowlingo/Connector.py
PyCrowlingo/Entities.py
PyCrowlingo/Errors.py
PyCrowlingo/Faq.py
PyCrowlingo/FileUploader.py
PyCrowlingo/Html.py
PyCrowlingo/Languages.py
PyCrowlingo/Model.py
PyCrowlingo/Multi.py
PyCrowlingo/Phrases.py
PyCrowlingo/SearchEngine.py
PyCrowlingo/Summary.py
PyCrowlingo/Syntax.py
PyCrowlingo/Texts.py
PyCrowlingo/User.py
PyCrowlingo/__init__.py
PyCrowlingo/ApiModels/Attributes.py
PyCrowlingo/ApiModels/Basic.py
PyCrowlingo/ApiModels/__init__.py
PyCrowlingo/ApiModels/Classifier/Requests.py
PyCrowlingo/ApiModels/Classifier/Responses.py
PyCrowlingo/ApiModels/Classifier/__init__.py
PyCrowlingo/ApiModels/Classifier/Examples/Requests.py
PyCrowlingo/ApiModels/Classifier/Examples/Responses.py
PyCrowlingo/ApiModels/Classifier/Examples/__init__.py
PyCrowlingo/ApiModels/Concepts/Requests.py
PyCrowlingo/ApiModels/Concepts/Responses.py
PyCrowlingo/ApiModels/Concepts/__init__.py
PyCrowlingo/ApiModels/Concepts/Examples/Requests.py
PyCrowlingo/ApiModels/Concepts/Examples/Responses.py
PyCrowlingo/ApiModels/Concepts/Examples/__init__.py
PyCrowlingo/ApiModels/Entities/Requests.py
PyCrowlingo/ApiModels/Entities/Responses.py
PyCrowlingo/ApiModels/Entities/__init__.py
PyCrowlingo/ApiModels/Entities/Examples/Requests.py
PyCrowlingo/ApiModels/Entities/Examples/Responses.py
PyCrowlingo/ApiModels/Entities/Examples/__init__.py
PyCrowlingo/ApiModels/Faq/Requests.py
PyCrowlingo/ApiModels/Faq/Responses.py
PyCrowlingo/ApiModels/Faq/__init__.py
PyCrowlingo/ApiModels/Faq/Examples/Requests.py
PyCrowlingo/ApiModels/Faq/Examples/Responses.py
PyCrowlingo/ApiModels/Faq/Examples/__init__.py
PyCrowlingo/ApiModels/Html/Requests.py
PyCrowlingo/ApiModels/Html/Responses.py
PyCrowlingo/ApiModels/Html/__init__.py
PyCrowlingo/ApiModels/Html/Examples/Requests.py
PyCrowlingo/ApiModels/Html/Examples/Responses.py
PyCrowlingo/ApiModels/Html/Examples/__init__.py
PyCrowlingo/ApiModels/Languages/Requests.py
PyCrowlingo-0.6.4.dist-info/METADATA
PyCrowlingo-0.6.4.dist-info/WHEEL
PyCrowlingo-0.6.4.dist-info/top_level.txt
PyCrowlingo-0.6.4.dist-info/RECORD
