Metadata-Version: 2.1
Name: PyCrowlingo
Version: 0.6.4
Summary: Official Crowlingo SDK. Access to all NLP and NLU services that analyze texts regardless of the language. 
Home-page: https://github.com/Crowlingo/PyCrowlingo/
Author: Jonas Bouaziz
License: copyright: Crowlingo
Platform: UNKNOWN
Requires-Dist: setuptools (~=47.1.1)
Requires-Dist: pydantic[email] (~=1.5.1)
Requires-Dist: typing (~=3.7.4.1)
Requires-Dist: requests (~=2.22.0)
Requires-Dist: lazy (~=1.4)
Provides-Extra: rasa
Requires-Dist: rasa ; extra == 'rasa'
